parepy_toolbox/__init__.py
parepy_toolbox/common_library.py
parepy_toolbox/pare.py
parepy_toolbox-2024.2.dist-info/METADATA
parepy_toolbox-2024.2.dist-info/WHEEL
parepy_toolbox-2024.2.dist-info/license.md
parepy_toolbox-2024.2.dist-info/top_level.txt
parepy_toolbox-2024.2.dist-info/RECORD
