Metadata-Version: 2.1
Name: parepy-toolbox
Version: 2024.2
Summary: The PAREpy is an easy-to-use environment for applying probabilistic modeling.
Home-page: https://wmpjrufg.github.io/PAREPY/
Author: ['Wanderlei Malaquias Pereira Junior', 'Donizetti Aparecido de Souza Junior', 'Romes Antônio Borges', 'Mateus Pereira da Silva', 'Murilo Carneiro Rodrigues', 'André Teófilo Beck', 'Daniel de Lima Araújo']
Author-email: wanderlei_junior@ufcat.edu.br
License: MIT License
Classifier: Development Status :: 4 - Beta
Classifier: Topic :: Education
Classifier: Topic :: Scientific/Engineering
Classifier: License :: OSI Approved :: MIT License
Classifier: Programming Language :: Python
License-File: license.md
Requires-Dist: numpy
Requires-Dist: scipy
Requires-Dist: pandas
